MetaDataScraper/FacebookScraper.py
MetaDataScraper/__init__.py
MetaDataScraper-1.0.4.dist-info/LICENCE
MetaDataScraper-1.0.4.dist-info/METADATA
MetaDataScraper-1.0.4.dist-info/WHEEL
MetaDataScraper-1.0.4.dist-info/top_level.txt
MetaDataScraper-1.0.4.dist-info/RECORD
